<window id="146">
	<defaultcontrol always="true"></defaultcontrol>
	<include>Window_OpenClose_Animation_Zoom</include>
	
	<coordinates>
		<system>1</system>
		<posx>225</posx>
		<posy>10</posy>
	</coordinates>
	<controls>
		<control type="image">
			<posx>0</posx>
			<posy>0</posy>
			<width>850</width>
			<height>60</height>
			<texture border="4">DialogHeader.png</texture>
		</control>
		<control type="label">
			<description>header label</description>
			<posx>15</posx>
			<posy>8</posy>
			<include>WindowTitleCommons</include>
			<width>820</width>
			<label>$LOCALIZE[24003]</label>
		</control>
		<control type="group">
			<posx>793</posx>
			<posy>0</posy>
			<include>DialogCloseButtonCommons</include>
		</control>
		<control type="image">
			<posx>0</posx>
			<posy>60</posy>
			<width>850</width>
			<height>630</height>
			<texture border="4">dialog_back_black2.png</texture>
		</control>

		<control type="group">
			<posy>67</posy>
			<posx>25</posx>
			<control type="label">
				<description>Addon Title value</description>
				<posx>0</posx>
				<posy>20</posy>
				<width>820</width>
				<height>22</height>
				<align>center</align>
				<aligny>center</aligny>
				<font>font28_title</font>
				<label>$INFO[ListItem.AddonName]</label>
				<textcolor>white</textcolor>
				<scroll>true</scroll>
			</control>
			<control type="image">
				<posx>0</posx>
				<posy>47</posy>
				<width>195</width>
				<height>225</height>
				<aspectratio>keep</aspectratio>
				<bordertexture border="7">ThumbShadow.png</bordertexture>
				<bordersize>7</bordersize>
				<texture background="true">$INFO[ListItem.Icon]</texture>
			</control>
			<control type="label">
				<posx>210</posx>
				<posy>65</posy>
				<width>410</width>
				<height>22</height>
				<font>font24_title</font>
				<textcolor>white</textcolor>
				<align>left</align>
				<aligny>center</aligny>
				<label>$LOCALIZE[21821]$INFO[Container(601).CurrentPage, ( $LOCALIZE[31024] ]$INFO[Container(601).NumPages,/, )]</label>
			</control>
			<control type="textbox" id="601">
				<description>Description Value for Albums</description>
				<posx>210</posx>
				<posy>90</posy>
				<width>600</width>
				<height>200</height>
				<font>font24</font>
				<textcolor>white</textcolor>
				<pagecontrol></pagecontrol>
				<label>$INFO[ListItem.AddonDescription]</label>
			</control>
			<control type="image">
				<posx>0</posx>
				<posy>292</posy>
				<width>820</width>
				<height>4</height>
				<texture>separator.png</texture>
			</control>
			<control type="group">
				<posx>0</posx>
				<posy>315</posy>
				<control type="label">
					<description>Type txt</description>
					<posx>200</posx>
					<posy>0</posy>
					<width>200</width>
					<height>25</height>
					<label>$LOCALIZE[146]</label>
					<align>right</align>
					<aligny>center</aligny>
					<font>font22_title</font>
					<textcolor>white</textcolor>
				</control>
				<control type="label">
					<description>Type Value</description>
					<posx>210</posx>
					<posy>0</posy>
					<width>770</width>
					<height>25</height>
					<label fallback="416">$INFO[ListItem.AddonType]</label>
					<align>left</align>
					<aligny>center</aligny>
					<font>font22</font>
					<textcolor>white</textcolor>
					<scroll>true</scroll>
				</control>
				<control type="label">
					<description>Author txt</description>
					<posx>200</posx>
					<posy>30</posy>
					<width>200</width>
					<height>25</height>
					<label>$LOCALIZE[21863]:</label>
					<align>right</align>
					<aligny>center</aligny>
					<font>font22_title</font>
					<textcolor>white</textcolor>
				</control>
				<control type="label">
					<description>Author Value</description>
					<posx>210</posx>
					<posy>30</posy>
					<width>770</width>
					<height>25</height>
					<label fallback="416">$INFO[ListItem.AddonCreator]</label>
					<align>left</align>
					<aligny>center</aligny>
					<font>font22</font>
					<textcolor>white</textcolor>
					<scroll>true</scroll>
				</control>
				<control type="label">
					<description>Version txt</description>
					<posx>200</posx>
					<posy>60</posy>
					<width>200</width>
					<height>25</height>
					<label>$LOCALIZE[24051]</label>
					<align>right</align>
					<aligny>center</aligny>
					<font>font22_title</font>
					<textcolor>white</textcolor>
				</control>
				<control type="label">
					<description>Version Value</description>
					<posx>210</posx>
					<posy>60</posy>
					<width>770</width>
					<height>25</height>
					<label fallback="416">$INFO[ListItem.AddonVersion]</label>
					<align>left</align>
					<aligny>center</aligny>
					<font>font22</font>
					<textcolor>white</textcolor>
					<scroll>true</scroll>
				</control>
				<control type="label">
					<description>Rating txt</description>
					<posx>200</posx>
					<posy>90</posy>
					<width>200</width>
					<height>25</height>
					<label>$LOCALIZE[563]:</label>
					<align>right</align>
					<aligny>center</aligny>
					<font>font22_title</font>
					<textcolor>white</textcolor>
				</control>
				<control type="image">
					<description>Rating value</description>
					<posx>208</posx>
					<posy>88</posy>
					<width>170</width>
					<height>34</height>
					<aspectratio align="left">keep</aspectratio>
					<texture>$INFO[ListItem.Property(Addon.StarRating),dark/left_rating/]</texture>
				</control>
				<control type="label">
					<description>Summary txt</description>
					<posx>200</posx>
					<posy>120</posy>
					<width>200</width>
					<height>25</height>
					<label>$LOCALIZE[20037]:</label>
					<align>right</align>
					<aligny>center</aligny>
					<font>font22_title</font>
					<textcolor>white</textcolor>
				</control>
				<control type="fadelabel">
					<description>Summary Value</description>
					<posx>210</posx>
					<posy>120</posy>
					<width>870</width>
					<height>25</height>
					<label fallback="416">$INFO[ListItem.AddonSummary]</label>
					<align>left</align>
					<aligny>center</aligny>
					<font>font22</font>
					<textcolor>white</textcolor>
					<scrollout>false</scrollout>
					<pauseatend>2000</pauseatend>
				</control>
				<control type="label">
					<description>Disclaimer txt</description>
					<posx>200</posx>
					<posy>150</posy>
					<width>200</width>
					<height>25</height>
					<label>$LOCALIZE[24052]:</label>
					<align>right</align>
					<aligny>center</aligny>
					<font>font22_title</font>
					<textcolor>white</textcolor>
				</control>
				<control type="textbox">
					<description>Disclaimer</description>
					<posx>210</posx>
					<posy>150</posy>
					<width>577</width>
					<height>60</height>
					<font>font22</font>
					<textcolor>white</textcolor>
					<label fallback="231">$INFO[ListItem.AddonDisclaimer]</label>
					<autoscroll time="2000" delay="3000" repeat="5000">true</autoscroll>
				</control>
				<control type="label">
					<description>Addon-ID</description>
					<posx>200</posx>
					<posy>180</posy>
					<width>200</width>
					<height>25</height>
					<label>Addon-ID:</label>
					<align>right</align>
					<aligny>center</aligny>
					<font>font22_title</font>
					<textcolor>white</textcolor>
				</control>
				<control type="textbox">
					<description>Addon-ID</description>
					<posx>210</posx>
					<posy>180</posy>
					<width>577</width>
					<height>60</height>
					<font>font22</font>
					<textcolor>white</textcolor>
					<label>$INFO[ListItem.Property(Addon.ID)]</label>
				</control>
			</control>
		</control>

		<control type="grouplist" id="9000">
			<posx>15</posx>
			<posy>610</posy>
			<width>820</width>
			<height>50</height>
			<itemgap>5</itemgap>
			<align>center</align>
			<orientation>horizontal</orientation>
			<onleft>9000</onleft>
			<onright>9000</onright>
			<onup>50</onup>
			<ondown>49</ondown>
			<control type="button" id ="6">
				<description>Enable Addon button</description>
				<width>160</width>
				<include>ButtonInfoDialogsCommonValues</include>
		        <font>font22</font>
				<label>24022</label>
			</control>
			<control type="button" id="7">
				<description>Disable Addon button</description>
				<width>160</width>
				<include>ButtonInfoDialogsCommonValues</include>
		        <font>font22</font>
				<label>24021</label>
			</control>
			<control type="button" id="9">
				<description>Addon Settings</description>
				<width>160</width>
				<include>ButtonInfoDialogsCommonValues</include>
		        <font>font22</font>
				<label>24020</label>
			</control>
			<control type="button" id="8">
				<description>Update Addon button</description>
				<width>160</width>
				<include>ButtonInfoDialogsCommonValues</include>
		        <font>font22</font>
				<label>24069</label>
			</control>
			<control type="button" id="10">
				<description>View dependencies</description>
				<width>160</width>
				<include>ButtonInfoDialogsCommonValues</include>
		        <font>font22</font>
				<label>39024</label>
			</control>
		</control>
<!-- 
		<control type="panel" id="50">
			<left>15</left>
			<posy>660</posy>
			<width>820</width>
			<height>233</height>
			<ondown>9000</ondown>
			<onup>9000</onup>
			<orientation>horizontal</orientation>
			<itemlayout height="225" width="405">
			<control type="image">
				<width>385</width>
				<height>220</height>
				<texture border="2" fallback="DefaultAddonNone.png" background="true">$INFO[ListItem.Icon]</texture>
 				<aspectratio>scale</aspectratio>
				<bordertexture colordiffuse="border_alpha">colors/black.png</bordertexture>
				<bordersize>4</bordersize>
			</control>
			</itemlayout>
			<focusedlayout height="225" width="405">
			<control type="image">
				<width>385</width>
				<height>220</height>
				<texture border="2" fallback="DefaultAddonNone.png" background="true">$INFO[ListItem.Icon]</texture>
				<aspectratio>scale</aspectratio>
				<bordertexture colordiffuse="border_alpha">colors/black.png</bordertexture>
				<bordersize>4</bordersize>
			</control>
			<control type="image">
				<width>385</width>
				<height>220</height>
				<texture border="8" colordiffuse="button_focus">buttons/thumbnail_focused.png</texture>
			</control>
			</focusedlayout>
  		</control>
 -->
		<control type="group">
			<include>VisibleFadeEffect</include>
			<control type="group">
				<visible>!String.IsEmpty(ListItem.AddonBroken)</visible>
				<posx>40</posx>
				<posy>720</posy>
				<control type="image">
					<description>background image</description>
					<posx>0</posx>
					<posy>0</posy>
					<width>920</width>
					<height>100</height>
					<texture border="20">OverlayDialogBackground.png</texture>
				</control>
				<control type="image">
					<description>Icon image</description>
					<posx>18</posx>
					<posy>18</posy>
					<width>64</width>
					<height>64</height>
					<texture>DefaultIconError.png</texture>
				</control>
				<control type="label">
					<description>header label</description>
					<posx>100</posx>
					<posy>15</posy>
					<width>800</width>
					<height>25</height>
					<font>font20_title</font>
					<label>24096</label>
					<align>left</align>
					<aligny>center</aligny>
					<textcolor>selected</textcolor>
				</control>
				<control type="textbox">
					<description>Reason label</description>
					<posx>100</posx>
					<posy>35</posy>
					<width>800</width>
					<height>50</height>
					<font>font20</font>
					<label>$INFO[ListItem.AddonBroken]</label>
					<align>left</align>
					<textcolor>white</textcolor>
				</control>
			</control>
		</control>
	</controls>
</window>
